pynougat.py
pynougat-0.0.2.dist-info/LICENSE
pynougat-0.0.2.dist-info/METADATA
pynougat-0.0.2.dist-info/WHEEL
pynougat-0.0.2.dist-info/RECORD
