Metadata-Version: 2.3
Name: pynougat
Version: 0.0.2
Summary: A lightweight type-safe Python utility for safely accessing deeply nested dictionary values
License: MIT
Keywords: nougat,pynougat,deep,nested,dictionary,access,path,traversal,type-safe
Author: Juan Sanchez
Author-email: jsanchez@sphire.co
Requires-Python: >=3.8
Classifier: Programming Language :: Python :: 3
Classifier: Operating System :: OS Independent
Project-URL: Homepage, https://github.com/sphireinc/pynougat
Project-URL: Issues, https://github.com/sphireinc/pynougat/issues
